osrparse/__init__.py
osrparse/replay.py
osrparse/strategies.py
osrparse/utils.py
osrparse-7.0.1.dist-info/LICENSE
osrparse-7.0.1.dist-info/METADATA
osrparse-7.0.1.dist-info/WHEEL
osrparse-7.0.1.dist-info/top_level.txt
osrparse-7.0.1.dist-info/RECORD
