Metadata-Version: 2.1
Name: osrparse
Version: 7.0.1
Summary: Parser for osr files and lzma replay streams for osu!
Author-email: Kevin Lim <kszlim@gmail.com>, Liam DeVoe <orionldevoe@gmail.com>
Project-URL: Homepage, https://github.com/kszlim/osu-replay-parser
Keywords: osu!,osr,replay,replays,parsing,parser,python
Classifier: Topic :: Games/Entertainment
Classifier: Topic :: Software Development :: Libraries
Classifier: Intended Audience :: Developers
Classifier: Operating System :: OS Independent
Classifier: Programming Language :: Python :: 3
License-File: LICENSE
Provides-Extra: dev
Requires-Dist: hypothesis ; extra == 'dev'
